{"highlevel":{"danceability":{"all":{"danceable":0.743734180927,"not_danceable":0.256265819073},"probability":0.743734180927,"value":"danceable","version":{"essentia":"2.1-beta1","essentia_build_sha":"8e24b98b71ad84f3024c7541412f02124a26d327","essentia_git_sha":"v2.1_beta1-228-g260734a","extractor":"music 1.0","gaia":"2.4-dev","gaia_git_sha":"857329b","models_essentia_git_sha":"v2.1_beta1"}},"gender":{"all":{"female":0.0721231773496,"male":0.927876830101},"probability":0.927876830101,"value":"male","version":{"essentia":"2.1-beta1","essentia_build_sha":"8e24b98b71ad84f3024c7541412f02124a26d327","essentia_git_sha":"v2.1_beta1-228-g260734a","extractor":"music 1.0","gaia":"2.4-dev","gaia_git_sha":"857329b","models_essentia_git_sha":"v2.1_beta1"}},"genre_dortmund":{"all":{"alternative":0.124992184341,"blues":0.0378865152597,"electronic":0.67862445116,"folkcountry":0.0260288845748,"funksoulrnb":0.00581260677427,"jazz":0.0148000549525,"pop":0.00729226600379,"raphiphop":0.00431238813326,"rock":0.100250646472},"probability":0.67862445116,"value":"electronic","version":{"essentia":"2.1-beta1","essentia_build_sha":"8e24b98b71ad84f3024c7541412f02124a26d327","essentia_git_sha":"v2.1_beta1-228-g260734a","extractor":"music 1.0","gaia":"2.4-dev","gaia_git_sha":"857329b","models_essentia_git_sha":"v2.1_beta1"}},"genre_electronic":{"all":{"ambient":0.509189069271,"dnb":0.0363321341574,"house":0.128146037459,"techno":0.0213305074722,"trance":0.305002242327},"probability":0.509189069271,"value":"ambient","version":{"essentia":"2.1-beta1","essentia_build_sha":"8e24b98b71ad84f3024c7541412f02124a26d327","essentia_git_sha":"v2.1_beta1-228-g260734a","extractor":"music 1.0","gaia":"2.4-dev","gaia_git_sha":"857329b","models_essentia_git_sha":"v2.1_beta1"}},"genre_rosamerica":{"all":{"cla":0.0148176001385,"dan":0.100779168308,"hip":0.057857926935,"jaz":0.0485932603478,"pop":0.435544788837,"rhy":0.0632923990488,"roc":0.260720551014,"spe":0.0183942969888},"probability":0.435544788837,"value":"pop","version":{"essentia":"2.1-beta1","essentia_build_sha":"8e24b98b71ad84f3024c7541412f02124a26d327","essentia_git_sha":"v2.1_beta1-228-g260734a","extractor":"music 1.0","gaia":"2.4-dev","gaia_git_sha":"857329b","models_essentia_git_sha":"v2.1_beta1"}},"genre_tzanetakis":{"all":{"blu":0.0626613423228,"cla":0.0348169617355,"cou":0.104475811124,"dis":0.0784321576357,"hip":0.15692435205,"jaz":0.313974827528,"met":0.0448166541755,"pop":0.0627359300852,"reg":0.0627360641956,"roc":0.0784258767962},"probability":0.313974827528,"value":"jaz","version":{"essentia":"2.1-beta1","essentia_build_sha":"8e24b98b71ad84f3024c7541412f02124a26d327","essentia_git_sha":"v2.1_beta1-228-g260734a","extractor":"music 1.0","gaia":"2.4-dev","gaia_git_sha":"857329b","models_essentia_git_sha":"v2.1_beta1"}},"ismir04_rhythm":{"all":{"ChaChaCha":0.911692321301,"Jive":0.00908426009119,"Quickstep":0.00185264635365,"Rumba-American":0.0102329878137,"Rumba-International":0.00156012398656,"Rumba-Misc":0.00226177275181,"Samba":0.00780346849933,"Tango":0.0452276319265,"VienneseWaltz":0.00953933317214,"Waltz":0.000745474069845},"probability":0.911692321301,"value":"ChaChaCha","version":{"essentia":"2.1-beta1","essentia_build_sha":"8e24b98b71ad84f3024c7541412f02124a26d327","essentia_git_sha":"v2.1_beta1-228-g260734a","extractor":"music 1.0","gaia":"2.4-dev","gaia_git_sha":"857329b","models_essentia_git_sha":"v2.1_beta1"}},"mood_acoustic":{"all":{"acoustic":0.0144336661324,"not_acoustic":0.985566318035},"probability":0.985566318035,"value":"not_acoustic","version":{"essentia":"2.1-beta1","essentia_build_sha":"8e24b98b71ad84f3024c7541412f02124a26d327","essentia_git_sha":"v2.1_beta1-228-g260734a","extractor":"music 1.0","gaia":"2.4-dev","gaia_git_sha":"857329b","models_essentia_git_sha":"v2.1_beta1"}},"mood_aggressive":{"all":{"aggressive":0.728894531727,"not_aggressive":0.271105438471},"probability":0.728894531727,"value":"aggressive","version":{"essentia":"2.1-beta1","essentia_build_sha":"8e24b98b71ad84f3024c7541412f02124a26d327","essentia_git_sha":"v2.1_beta1-228-g260734a","extractor":"music 1.0","gaia":"2.4-dev","gaia_git_sha":"857329b","models_essentia_git_sha":"v2.1_beta1"}},"mood_electronic":{"all":{"electronic":0.7969404459,"not_electronic":0.203059569001},"probability":0.7969404459,"value":"electronic","version":{"essentia":"2.1-beta1","essentia_build_sha":"8e24b98b71ad84f3024c7541412f02124a26d327","essentia_git_sha":"v2.1_beta1-228-g260734a","extractor":"music 1.0","gaia":"2.4-dev","gaia_git_sha":"857329b","models_essentia_git_sha":"v2.1_beta1"}},"mood_happy":{"all":{"happy":0.551179409027,"not_happy":0.448820620775},"probability":0.551179409027,"value":"happy","version":{"essentia":"2.1-beta1","essentia_build_sha":"8e24b98b71ad84f3024c7541412f02124a26d327","essentia_git_sha":"v2.1_beta1-228-g260734a","extractor":"music 1.0","gaia":"2.4-dev","gaia_git_sha":"857329b","models_essentia_git_sha":"v2.1_beta1"}},"mood_party":{"all":{"not_party":0.109389007092,"party":0.890610992908},"probability":0.890610992908,"value":"party","version":{"essentia":"2.1-beta1","essentia_build_sha":"8e24b98b71ad84f3024c7541412f02124a26d327","essentia_git_sha":"v2.1_beta1-228-g260734a","extractor":"music 1.0","gaia":"2.4-dev","gaia_git_sha":"857329b","models_essentia_git_sha":"v2.1_beta1"}},"mood_relaxed":{"all":{"not_relaxed":0.459645241499,"relaxed":0.540354788303},"probability":0.540354788303,"value":"relaxed","version":{"essentia":"2.1-beta1","essentia_build_sha":"8e24b98b71ad84f3024c7541412f02124a26d327","essentia_git_sha":"v2.1_beta1-228-g260734a","extractor":"music 1.0","gaia":"2.4-dev","gaia_git_sha":"857329b","models_essentia_git_sha":"v2.1_beta1"}},"mood_sad":{"all":{"not_sad":0.932248055935,"sad":0.0677519440651},"probability":0.932248055935,"value":"not_sad","version":{"essentia":"2.1-beta1","essentia_build_sha":"8e24b98b71ad84f3024c7541412f02124a26d327","essentia_git_sha":"v2.1_beta1-228-g260734a","extractor":"music 1.0","gaia":"2.4-dev","gaia_git_sha":"857329b","models_essentia_git_sha":"v2.1_beta1"}},"moods_mirex":{"all":{"Cluster1":0.213334068656,"Cluster2":0.089700460434,"Cluster3":0.037795856595,"Cluster4":0.0752338245511,"Cluster5":0.583935797215},"probability":0.583935797215,"value":"Cluster5","version":{"essentia":"2.1-beta1","essentia_build_sha":"8e24b98b71ad84f3024c7541412f02124a26d327","essentia_git_sha":"v2.1_beta1-228-g260734a","extractor":"music 1.0","gaia":"2.4-dev","gaia_git_sha":"857329b","models_essentia_git_sha":"v2.1_beta1"}},"timbre":{"all":{"bright":0.118448160589,"dark":0.881551861763},"probability":0.881551861763,"value":"dark","version":{"essentia":"2.1-beta1","essentia_build_sha":"8e24b98b71ad84f3024c7541412f02124a26d327","essentia_git_sha":"v2.1_beta1-228-g260734a","extractor":"music 1.0","gaia":"2.4-dev","gaia_git_sha":"857329b","models_essentia_git_sha":"v2.1_beta1"}},"tonal_atonal":{"all":{"atonal":0.935222566128,"tonal":0.0647774487734},"probability":0.935222566128,"value":"atonal","version":{"essentia":"2.1-beta1","essentia_build_sha":"8e24b98b71ad84f3024c7541412f02124a26d327","essentia_git_sha":"v2.1_beta1-228-g260734a","extractor":"music 1.0","gaia":"2.4-dev","gaia_git_sha":"857329b","models_essentia_git_sha":"v2.1_beta1"}},"voice_instrumental":{"all":{"instrumental":0.763610720634,"voice":0.236389294267},"probability":0.763610720634,"value":"instrumental","version":{"essentia":"2.1-beta1","essentia_build_sha":"8e24b98b71ad84f3024c7541412f02124a26d327","essentia_git_sha":"v2.1_beta1-228-g260734a","extractor":"music 1.0","gaia":"2.4-dev","gaia_git_sha":"857329b","models_essentia_git_sha":"v2.1_beta1"}}},"metadata":{"audio_properties":{"analysis_sample_rate":44100,"bit_rate":0,"codec":"flac","downmix":"mix","equal_loudness":0,"length":143.759994507,"lossless":1,"md5_encoded":"0fcacae9372026afea58bbcdb76ccba2","replay_gain":-16.127035141},"tags":{"album":["Nirvana"],"albumartist":["Nirvana"],"albumartistsort":["Nirvana"],"artist":["Nirvana"],"artistsort":["Nirvana"],"asin":["B00006V9A0"],"date":["2002-10-28"],"file_name":"03 Been a Son (1).flac","format":["CD"],"genre":["Grunge"],"isrc":["USUG10200085"],"label":["DGC Records"],"language":["eng"],"musicbrainz_albumartistid":["5b11f4ce-a62d-471e-81fc-a69a8278c7da"],"musicbrainz_albumid":["653988c5-c79f-4b24-840a-6b1d21144405"],"musicbrainz_artistid":["5b11f4ce-a62d-471e-81fc-a69a8278c7da"],"musicbrainz_recordingid":["5cccdd85-fef1-4210-a14b-1ed94a7923b4"],"releasecountry":["GB"],"releasestatus":["official"],"releasetype":["compilation"],"replaygain_album_gain":["-8.66 dB"],"replaygain_album_peak":["1.00000000"],"replaygain_reference_loudness":["89.0 dB"],"replaygain_track_gain":["-10.60 dB"],"replaygain_track_peak":["0.98870850"],"script":["Latn"],"title":["Been a Son"],"totaltracks":["15"],"tracknumber":["3"],"tracktotal":["15"]},"version":{"highlevel":{"essentia":"2.1-beta1","essentia_build_sha":"8e24b98b71ad84f3024c7541412f02124a26d327","essentia_git_sha":"v2.1_beta1-228-g260734a","extractor":"music 1.0","gaia":"2.4-dev","gaia_git_sha":"857329b","models_essentia_git_sha":"v2.1_beta1"},"lowlevel":{"essentia":"2.1-beta1","essentia_build_sha":"d95b123ab7c93145a6f110a2dd6bea92b4529a00","essentia_git_sha":"v2.1_beta1-6-g5578087-dirty","extractor":"music 1.0"}}}}