{"highlevel":{"danceability":{"all":{"danceable":0.790380239487,"not_danceable":0.209619730711},"probability":0.790380239487,"value":"danceable","version":{"essentia":"2.1-beta1","essentia_build_sha":"8e24b98b71ad84f3024c7541412f02124a26d327","essentia_git_sha":"v2.1_beta1-228-g260734a","extractor":"music 1.0","gaia":"2.4-dev","gaia_git_sha":"857329b","models_essentia_git_sha":"v2.1_beta1"}},"gender":{"all":{"female":0.00747193908319,"male":0.99252808094},"probability":0.99252808094,"value":"male","version":{"essentia":"2.1-beta1","essentia_build_sha":"8e24b98b71ad84f3024c7541412f02124a26d327","essentia_git_sha":"v2.1_beta1-228-g260734a","extractor":"music 1.0","gaia":"2.4-dev","gaia_git_sha":"857329b","models_essentia_git_sha":"v2.1_beta1"}},"genre_dortmund":{"all":{"alternative":0.115354083478,"blues":0.0203772597015,"electronic":0.0593668743968,"folkcountry":0.177585437894,"funksoulrnb":0.00858838204294,"jazz":0.0209470465779,"pop":0.0334574095905,"raphiphop":0.0139806317165,"rock":0.550342857838},"probability":0.550342857838,"value":"rock","version":{"essentia":"2.1-beta1","essentia_build_sha":"8e24b98b71ad84f3024c7541412f02124a26d327","essentia_git_sha":"v2.1_beta1-228-g260734a","extractor":"music 1.0","gaia":"2.4-dev","gaia_git_sha":"857329b","models_essentia_git_sha":"v2.1_beta1"}},"genre_electronic":{"all":{"ambient":0.389994621277,"dnb":0.286323934793,"house":0.101243682206,"techno":0.02535703592,"trance":0.197080731392},"probability":0.389994621277,"value":"ambient","version":{"essentia":"2.1-beta1","essentia_build_sha":"8e24b98b71ad84f3024c7541412f02124a26d327","essentia_git_sha":"v2.1_beta1-228-g260734a","extractor":"music 1.0","gaia":"2.4-dev","gaia_git_sha":"857329b","models_essentia_git_sha":"v2.1_beta1"}},"genre_rosamerica":{"all":{"cla":0.0170852281153,"dan":0.129032313824,"hip":0.055059608072,"jaz":0.0286175683141,"pop":0.346087306738,"rhy":0.130798101425,"roc":0.281661182642,"spe":0.0116586815566},"probability":0.346087306738,"value":"pop","version":{"essentia":"2.1-beta1","essentia_build_sha":"8e24b98b71ad84f3024c7541412f02124a26d327","essentia_git_sha":"v2.1_beta1-228-g260734a","extractor":"music 1.0","gaia":"2.4-dev","gaia_git_sha":"857329b","models_essentia_git_sha":"v2.1_beta1"}},"genre_tzanetakis":{"all":{"blu":0.0626613423228,"cla":0.0348169617355,"cou":0.104475811124,"dis":0.0784321576357,"hip":0.15692435205,"jaz":0.313974827528,"met":0.0448166541755,"pop":0.0627359300852,"reg":0.0627360641956,"roc":0.0784258767962},"probability":0.313974827528,"value":"jaz","version":{"essentia":"2.1-beta1","essentia_build_sha":"8e24b98b71ad84f3024c7541412f02124a26d327","essentia_git_sha":"v2.1_beta1-228-g260734a","extractor":"music 1.0","gaia":"2.4-dev","gaia_git_sha":"857329b","models_essentia_git_sha":"v2.1_beta1"}},"ismir04_rhythm":{"all":{"ChaChaCha":0.188006430864,"Jive":0.317705690861,"Quickstep":0.0393139645457,"Rumba-American":0.00852047745138,"Rumba-International":0.0549919046462,"Rumba-Misc":0.0184742696583,"Samba":0.259074091911,"Tango":0.00537929544225,"VienneseWaltz":0.0858720988035,"Waltz":0.0226617567241},"probability":0.317705690861,"value":"Jive","version":{"essentia":"2.1-beta1","essentia_build_sha":"8e24b98b71ad84f3024c7541412f02124a26d327","essentia_git_sha":"v2.1_beta1-228-g260734a","extractor":"music 1.0","gaia":"2.4-dev","gaia_git_sha":"857329b","models_essentia_git_sha":"v2.1_beta1"}},"mood_acoustic":{"all":{"acoustic":0.376651316881,"not_acoustic":0.623348653316},"probability":0.623348653316,"value":"not_acoustic","version":{"essentia":"2.1-beta1","essentia_build_sha":"8e24b98b71ad84f3024c7541412f02124a26d327","essentia_git_sha":"v2.1_beta1-228-g260734a","extractor":"music 1.0","gaia":"2.4-dev","gaia_git_sha":"857329b","models_essentia_git_sha":"v2.1_beta1"}},"mood_aggressive":{"all":{"aggressive":0.112465955317,"not_aggressive":0.887534022331},"probability":0.887534022331,"value":"not_aggressive","version":{"essentia":"2.1-beta1","essentia_build_sha":"8e24b98b71ad84f3024c7541412f02124a26d327","essentia_git_sha":"v2.1_beta1-228-g260734a","extractor":"music 1.0","gaia":"2.4-dev","gaia_git_sha":"857329b","models_essentia_git_sha":"v2.1_beta1"}},"mood_electronic":{"all":{"electronic":0.380349427462,"not_electronic":0.619650602341},"probability":0.619650602341,"value":"not_electronic","version":{"essentia":"2.1-beta1","essentia_build_sha":"8e24b98b71ad84f3024c7541412f02124a26d327","essentia_git_sha":"v2.1_beta1-228-g260734a","extractor":"music 1.0","gaia":"2.4-dev","gaia_git_sha":"857329b","models_essentia_git_sha":"v2.1_beta1"}},"mood_happy":{"all":{"happy":0.270152211189,"not_happy":0.729847788811},"probability":0.729847788811,"value":"not_happy","version":{"essentia":"2.1-beta1","essentia_build_sha":"8e24b98b71ad84f3024c7541412f02124a26d327","essentia_git_sha":"v2.1_beta1-228-g260734a","extractor":"music 1.0","gaia":"2.4-dev","gaia_git_sha":"857329b","models_essentia_git_sha":"v2.1_beta1"}},"mood_party":{"all":{"not_party":0.749107122421,"party":0.250892877579},"probability":0.749107122421,"value":"not_party","version":{"essentia":"2.1-beta1","essentia_build_sha":"8e24b98b71ad84f3024c7541412f02124a26d327","essentia_git_sha":"v2.1_beta1-228-g260734a","extractor":"music 1.0","gaia":"2.4-dev","gaia_git_sha":"857329b","models_essentia_git_sha":"v2.1_beta1"}},"mood_relaxed":{"all":{"not_relaxed":0.418972969055,"relaxed":0.581027030945},"probability":0.581027030945,"value":"relaxed","version":{"essentia":"2.1-beta1","essentia_build_sha":"8e24b98b71ad84f3024c7541412f02124a26d327","essentia_git_sha":"v2.1_beta1-228-g260734a","extractor":"music 1.0","gaia":"2.4-dev","gaia_git_sha":"857329b","models_essentia_git_sha":"v2.1_beta1"}},"mood_sad":{"all":{"not_sad":0.65127068758,"sad":0.34872931242},"probability":0.65127068758,"value":"not_sad","version":{"essentia":"2.1-beta1","essentia_build_sha":"8e24b98b71ad84f3024c7541412f02124a26d327","essentia_git_sha":"v2.1_beta1-228-g260734a","extractor":"music 1.0","gaia":"2.4-dev","gaia_git_sha":"857329b","models_essentia_git_sha":"v2.1_beta1"}},"moods_mirex":{"all":{"Cluster1":0.234618067741,"Cluster2":0.210821568966,"Cluster3":0.0762064009905,"Cluster4":0.15567432344,"Cluster5":0.322679638863},"probability":0.322679638863,"value":"Cluster5","version":{"essentia":"2.1-beta1","essentia_build_sha":"8e24b98b71ad84f3024c7541412f02124a26d327","essentia_git_sha":"v2.1_beta1-228-g260734a","extractor":"music 1.0","gaia":"2.4-dev","gaia_git_sha":"857329b","models_essentia_git_sha":"v2.1_beta1"}},"timbre":{"all":{"bright":0.874151170254,"dark":0.125848814845},"probability":0.874151170254,"value":"bright","version":{"essentia":"2.1-beta1","essentia_build_sha":"8e24b98b71ad84f3024c7541412f02124a26d327","essentia_git_sha":"v2.1_beta1-228-g260734a","extractor":"music 1.0","gaia":"2.4-dev","gaia_git_sha":"857329b","models_essentia_git_sha":"v2.1_beta1"}},"tonal_atonal":{"all":{"atonal":0.349902749062,"tonal":0.650097250938},"probability":0.650097250938,"value":"tonal","version":{"essentia":"2.1-beta1","essentia_build_sha":"8e24b98b71ad84f3024c7541412f02124a26d327","essentia_git_sha":"v2.1_beta1-228-g260734a","extractor":"music 1.0","gaia":"2.4-dev","gaia_git_sha":"857329b","models_essentia_git_sha":"v2.1_beta1"}},"voice_instrumental":{"all":{"instrumental":0.00219827028923,"voice":0.997801721096},"probability":0.997801721096,"value":"voice","version":{"essentia":"2.1-beta1","essentia_build_sha":"8e24b98b71ad84f3024c7541412f02124a26d327","essentia_git_sha":"v2.1_beta1-228-g260734a","extractor":"music 1.0","gaia":"2.4-dev","gaia_git_sha":"857329b","models_essentia_git_sha":"v2.1_beta1"}}},"metadata":{"audio_properties":{"analysis_sample_rate":44100,"bit_rate":0,"codec":"flac","downmix":"mix","equal_loudness":0,"length":113.800003052,"lossless":1,"md5_encoded":"2efcdbd00e28df152e9fc2c9e0c619a8","replay_gain":-14.6597709656},"tags":{"acoustid_id":["b03e40e9-4992-4676-9e22-b206ac480fdd"],"album":["Punk-O-Rama, Volume 3"],"albumartist":["Various Artists"],"artist":["Osker"],"date":["1998-06-20"],"discnumber":["1"],"disctotal":["1"],"file_name":"19 - Osker - Alright.flac","musicbrainz_albumartistid":["89ad4ac3-39f7-470e-963a-56509c546377"],"musicbrainz_albumid":["8f689279-20ad-4f08-a78e-7df391da1f04"],"musicbrainz_artistid":["67afdc03-6b4d-47a3-966e-b67b8acbc9ea"],"musicbrainz_recordingid":["5ffa073e-741e-4694-bd59-a0fdbd8e768b"],"musicbrainz_releasegroupid":["e208bcfd-f4da-3c5d-a36e-672605ae306e"],"replaygain_album_gain":["-9.69 dB"],"replaygain_album_peak":["0.999969"],"replaygain_track_gain":["-9.85 dB"],"replaygain_track_peak":["0.977325"],"title":["Alright"],"tracknumber":["19"],"tracktotal":["27"]},"version":{"highlevel":{"essentia":"2.1-beta1","essentia_build_sha":"8e24b98b71ad84f3024c7541412f02124a26d327","essentia_git_sha":"v2.1_beta1-228-g260734a","extractor":"music 1.0","gaia":"2.4-dev","gaia_git_sha":"857329b","models_essentia_git_sha":"v2.1_beta1"},"lowlevel":{"essentia":"2.1-beta1","essentia_build_sha":"46c2b6830b139c2e69ed9f3e0d9145e1b8fbae31","essentia_git_sha":"v2.1_beta1-6-g5578087","extractor":"music 1.0"}}}}