{"highlevel":{"danceability":{"all":{"danceable":0.0622596144676,"not_danceable":0.937740385532},"probability":0.937740385532,"value":"not_danceable","version":{"essentia":"2.1-beta1","essentia_build_sha":"8e24b98b71ad84f3024c7541412f02124a26d327","essentia_git_sha":"v2.1_beta1-228-g260734a","extractor":"music 1.0","gaia":"2.4-dev","gaia_git_sha":"857329b","models_essentia_git_sha":"v2.1_beta1"}},"gender":{"all":{"female":0.420499652624,"male":0.579500317574},"probability":0.579500317574,"value":"male","version":{"essentia":"2.1-beta1","essentia_build_sha":"8e24b98b71ad84f3024c7541412f02124a26d327","essentia_git_sha":"v2.1_beta1-228-g260734a","extractor":"music 1.0","gaia":"2.4-dev","gaia_git_sha":"857329b","models_essentia_git_sha":"v2.1_beta1"}},"genre_dortmund":{"all":{"alternative":0.0576354376972,"blues":0.408229589462,"electronic":0.299164146185,"folkcountry":0.0732514113188,"funksoulrnb":0.0095854587853,"jazz":0.0689629167318,"pop":0.0126526858658,"raphiphop":0.00735090207309,"rock":0.063167437911},"probability":0.408229589462,"value":"blues","version":{"essentia":"2.1-beta1","essentia_build_sha":"8e24b98b71ad84f3024c7541412f02124a26d327","essentia_git_sha":"v2.1_beta1-228-g260734a","extractor":"music 1.0","gaia":"2.4-dev","gaia_git_sha":"857329b","models_essentia_git_sha":"v2.1_beta1"}},"genre_electronic":{"all":{"ambient":0.942105770111,"dnb":0.00756254931912,"house":0.037789709866,"techno":0.00759150087833,"trance":0.00495045352727},"probability":0.942105770111,"value":"ambient","version":{"essentia":"2.1-beta1","essentia_build_sha":"8e24b98b71ad84f3024c7541412f02124a26d327","essentia_git_sha":"v2.1_beta1-228-g260734a","extractor":"music 1.0","gaia":"2.4-dev","gaia_git_sha":"857329b","models_essentia_git_sha":"v2.1_beta1"}},"genre_rosamerica":{"all":{"cla":0.733947753906,"dan":0.00159736652859,"hip":0.0263913851231,"jaz":0.211713865399,"pop":0.0034037376754,"rhy":0.0178472660482,"roc":0.00254126079381,"spe":0.00255737802945},"probability":0.733947753906,"value":"cla","version":{"essentia":"2.1-beta1","essentia_build_sha":"8e24b98b71ad84f3024c7541412f02124a26d327","essentia_git_sha":"v2.1_beta1-228-g260734a","extractor":"music 1.0","gaia":"2.4-dev","gaia_git_sha":"857329b","models_essentia_git_sha":"v2.1_beta1"}},"genre_tzanetakis":{"all":{"blu":0.055673841387,"cla":0.110624030232,"cou":0.071824580431,"dis":0.0749653205276,"hip":0.0517191886902,"jaz":0.119716331363,"met":0.0750680193305,"pop":0.179602891207,"reg":0.0800935700536,"roc":0.180712223053},"probability":0.180712223053,"value":"roc","version":{"essentia":"2.1-beta1","essentia_build_sha":"8e24b98b71ad84f3024c7541412f02124a26d327","essentia_git_sha":"v2.1_beta1-228-g260734a","extractor":"music 1.0","gaia":"2.4-dev","gaia_git_sha":"857329b","models_essentia_git_sha":"v2.1_beta1"}},"ismir04_rhythm":{"all":{"ChaChaCha":0.000141845041071,"Jive":0.000278905965388,"Quickstep":0.0000222927064897,"Rumba-American":0.0000437034468632,"Rumba-International":0.000042186002247,"Rumba-Misc":0.0000348860921804,"Samba":0.000517304230016,"Tango":0.998625516891,"VienneseWaltz":0.000224038623855,"Waltz":0.0000693286856404},"probability":0.998625516891,"value":"Tango","version":{"essentia":"2.1-beta1","essentia_build_sha":"8e24b98b71ad84f3024c7541412f02124a26d327","essentia_git_sha":"v2.1_beta1-228-g260734a","extractor":"music 1.0","gaia":"2.4-dev","gaia_git_sha":"857329b","models_essentia_git_sha":"v2.1_beta1"}},"mood_acoustic":{"all":{"acoustic":0.166906505823,"not_acoustic":0.833093523979},"probability":0.833093523979,"value":"not_acoustic","version":{"essentia":"2.1-beta1","essentia_build_sha":"8e24b98b71ad84f3024c7541412f02124a26d327","essentia_git_sha":"v2.1_beta1-228-g260734a","extractor":"music 1.0","gaia":"2.4-dev","gaia_git_sha":"857329b","models_essentia_git_sha":"v2.1_beta1"}},"mood_aggressive":{"all":{"aggressive":0.142105683684,"not_aggressive":0.857894301414},"probability":0.857894301414,"value":"not_aggressive","version":{"essentia":"2.1-beta1","essentia_build_sha":"8e24b98b71ad84f3024c7541412f02124a26d327","essentia_git_sha":"v2.1_beta1-228-g260734a","extractor":"music 1.0","gaia":"2.4-dev","gaia_git_sha":"857329b","models_essentia_git_sha":"v2.1_beta1"}},"mood_electronic":{"all":{"electronic":0.629588067532,"not_electronic":0.370411932468},"probability":0.629588067532,"value":"electronic","version":{"essentia":"2.1-beta1","essentia_build_sha":"8e24b98b71ad84f3024c7541412f02124a26d327","essentia_git_sha":"v2.1_beta1-228-g260734a","extractor":"music 1.0","gaia":"2.4-dev","gaia_git_sha":"857329b","models_essentia_git_sha":"v2.1_beta1"}},"mood_happy":{"all":{"happy":0.0870018079877,"not_happy":0.912998199463},"probability":0.912998199463,"value":"not_happy","version":{"essentia":"2.1-beta1","essentia_build_sha":"8e24b98b71ad84f3024c7541412f02124a26d327","essentia_git_sha":"v2.1_beta1-228-g260734a","extractor":"music 1.0","gaia":"2.4-dev","gaia_git_sha":"857329b","models_essentia_git_sha":"v2.1_beta1"}},"mood_party":{"all":{"not_party":0.74026453495,"party":0.259735435247},"probability":0.74026453495,"value":"not_party","version":{"essentia":"2.1-beta1","essentia_build_sha":"8e24b98b71ad84f3024c7541412f02124a26d327","essentia_git_sha":"v2.1_beta1-228-g260734a","extractor":"music 1.0","gaia":"2.4-dev","gaia_git_sha":"857329b","models_essentia_git_sha":"v2.1_beta1"}},"mood_relaxed":{"all":{"not_relaxed":0.0440904349089,"relaxed":0.95590955019},"probability":0.95590955019,"value":"relaxed","version":{"essentia":"2.1-beta1","essentia_build_sha":"8e24b98b71ad84f3024c7541412f02124a26d327","essentia_git_sha":"v2.1_beta1-228-g260734a","extractor":"music 1.0","gaia":"2.4-dev","gaia_git_sha":"857329b","models_essentia_git_sha":"v2.1_beta1"}},"mood_sad":{"all":{"not_sad":0.250431656837,"sad":0.749568343163},"probability":0.749568343163,"value":"sad","version":{"essentia":"2.1-beta1","essentia_build_sha":"8e24b98b71ad84f3024c7541412f02124a26d327","essentia_git_sha":"v2.1_beta1-228-g260734a","extractor":"music 1.0","gaia":"2.4-dev","gaia_git_sha":"857329b","models_essentia_git_sha":"v2.1_beta1"}},"moods_mirex":{"all":{"Cluster1":0.148752465844,"Cluster2":0.303449243307,"Cluster3":0.108191423118,"Cluster4":0.213554352522,"Cluster5":0.226052522659},"probability":0.303449243307,"value":"Cluster2","version":{"essentia":"2.1-beta1","essentia_build_sha":"8e24b98b71ad84f3024c7541412f02124a26d327","essentia_git_sha":"v2.1_beta1-228-g260734a","extractor":"music 1.0","gaia":"2.4-dev","gaia_git_sha":"857329b","models_essentia_git_sha":"v2.1_beta1"}},"timbre":{"all":{"bright":0.115073792636,"dark":0.884926199913},"probability":0.884926199913,"value":"dark","version":{"essentia":"2.1-beta1","essentia_build_sha":"8e24b98b71ad84f3024c7541412f02124a26d327","essentia_git_sha":"v2.1_beta1-228-g260734a","extractor":"music 1.0","gaia":"2.4-dev","gaia_git_sha":"857329b","models_essentia_git_sha":"v2.1_beta1"}},"tonal_atonal":{"all":{"atonal":0.979953169823,"tonal":0.0200468115509},"probability":0.979953169823,"value":"atonal","version":{"essentia":"2.1-beta1","essentia_build_sha":"8e24b98b71ad84f3024c7541412f02124a26d327","essentia_git_sha":"v2.1_beta1-228-g260734a","extractor":"music 1.0","gaia":"2.4-dev","gaia_git_sha":"857329b","models_essentia_git_sha":"v2.1_beta1"}},"voice_instrumental":{"all":{"instrumental":0.0716269612312,"voice":0.928373038769},"probability":0.928373038769,"value":"voice","version":{"essentia":"2.1-beta1","essentia_build_sha":"8e24b98b71ad84f3024c7541412f02124a26d327","essentia_git_sha":"v2.1_beta1-228-g260734a","extractor":"music 1.0","gaia":"2.4-dev","gaia_git_sha":"857329b","models_essentia_git_sha":"v2.1_beta1"}}},"metadata":{"audio_properties":{"analysis_sample_rate":44100,"bit_rate":0,"codec":"flac","downmix":"mix","equal_loudness":0,"length":181.57333374,"lossless":1,"md5_encoded":"7247127d080adebc0fb16c33ed9ddd5c","replay_gain":-9.18286132812},"tags":{"acoustid_id":["1804704d-5933-4fdc-9585-e320987235ad"],"album":["Slipstream"],"albumartist":["Elmer Bernstein"],"albumartistsort":["Bernstein, Elmer"],"artists":["Elmer Bernstein"],"artistsort":["Bernstein, Elmer"],"asin":["B004VJYVJM"],"barcode":["827034003926"],"catalognumber":["PRD 039"],"date":["2011-04-05"],"discnumber":["1"],"disctotal":["1"],"file_name":"02 Escape.flac","label":["Perseverance Records"],"media":["CD"],"musicbrainz_albumartistid":["e2c7d7a5-b520-4232-b7cf-aaceead17b6c"],"musicbrainz_albumid":["222b3fc0-ff58-42ea-86c8-1d4830d02ec0"],"musicbrainz_artistid":["e2c7d7a5-b520-4232-b7cf-aaceead17b6c"],"musicbrainz_recordingid":["9ba379e4-6a77-4046-a554-3eb0e5e33cc8"],"musicbrainz_releasegroupid":["78fe79f5-ef5a-4040-9fff-58061ae813a0"],"musicbrainz_releasetrackid":["c171548a-fc57-31b5-a8e9-474cdf5ba79f"],"originaldate":["2011-04-05"],"releasecountry":["US"],"releasestatus":["official"],"releasetype":["album","soundtrack"],"script":["Latn"],"title":["Escape"],"totaldiscs":["1"],"totaltracks":["11"],"tracknumber":["2"],"tracktotal":["11"]},"version":{"highlevel":{"essentia":"2.1-beta1","essentia_build_sha":"8e24b98b71ad84f3024c7541412f02124a26d327","essentia_git_sha":"v2.1_beta1-228-g260734a","extractor":"music 1.0","gaia":"2.4-dev","gaia_git_sha":"857329b","models_essentia_git_sha":"v2.1_beta1"},"lowlevel":{"essentia":"2.1-beta1","essentia_build_sha":"7f154e5731828a63663f0144680ef47bd640f88b","essentia_git_sha":"v2.1_beta1-6-g5578087","extractor":"music 1.0"}}}}