{"highlevel":{"danceability":{"all":{"danceable":0.0514660440385,"not_danceable":0.948533952236},"probability":0.948533952236,"value":"not_danceable","version":{"essentia":"2.1-beta1","essentia_build_sha":"8e24b98b71ad84f3024c7541412f02124a26d327","essentia_git_sha":"v2.1_beta1-228-g260734a","extractor":"music 1.0","gaia":"2.4-dev","gaia_git_sha":"857329b","models_essentia_git_sha":"v2.1_beta1"}},"gender":{"all":{"female":0.978014171124,"male":0.0219858512282},"probability":0.978014171124,"value":"female","version":{"essentia":"2.1-beta1","essentia_build_sha":"8e24b98b71ad84f3024c7541412f02124a26d327","essentia_git_sha":"v2.1_beta1-228-g260734a","extractor":"music 1.0","gaia":"2.4-dev","gaia_git_sha":"857329b","models_essentia_git_sha":"v2.1_beta1"}},"genre_dortmund":{"all":{"alternative":0.051295157522,"blues":0.0110132787377,"electronic":0.878076851368,"folkcountry":0.0413865298033,"funksoulrnb":0.000774908112362,"jazz":0.00402224995196,"pop":0.00344271608628,"raphiphop":0.00057713733986,"rock":0.00941119808704},"probability":0.878076851368,"value":"electronic","version":{"essentia":"2.1-beta1","essentia_build_sha":"8e24b98b71ad84f3024c7541412f02124a26d327","essentia_git_sha":"v2.1_beta1-228-g260734a","extractor":"music 1.0","gaia":"2.4-dev","gaia_git_sha":"857329b","models_essentia_git_sha":"v2.1_beta1"}},"genre_electronic":{"all":{"ambient":0.790467262268,"dnb":0.00731479516253,"house":0.160596728325,"techno":0.00978508684784,"trance":0.0318361222744},"probability":0.790467262268,"value":"ambient","version":{"essentia":"2.1-beta1","essentia_build_sha":"8e24b98b71ad84f3024c7541412f02124a26d327","essentia_git_sha":"v2.1_beta1-228-g260734a","extractor":"music 1.0","gaia":"2.4-dev","gaia_git_sha":"857329b","models_essentia_git_sha":"v2.1_beta1"}},"genre_rosamerica":{"all":{"cla":0.0283495783806,"dan":0.00544171314687,"hip":0.00255400524475,"jaz":0.136963054538,"pop":0.552735745907,"rhy":0.233720332384,"roc":0.0348562970757,"spe":0.00537927122787},"probability":0.552735745907,"value":"pop","version":{"essentia":"2.1-beta1","essentia_build_sha":"8e24b98b71ad84f3024c7541412f02124a26d327","essentia_git_sha":"v2.1_beta1-228-g260734a","extractor":"music 1.0","gaia":"2.4-dev","gaia_git_sha":"857329b","models_essentia_git_sha":"v2.1_beta1"}},"genre_tzanetakis":{"all":{"blu":0.063918299973,"cla":0.0355145335197,"cou":0.0799135118723,"dis":0.0639404505491,"hip":0.159863680601,"jaz":0.319764941931,"met":0.0799313560128,"pop":0.0799273103476,"reg":0.0639410167933,"roc":0.053284894675},"probability":0.319764941931,"value":"jaz","version":{"essentia":"2.1-beta1","essentia_build_sha":"8e24b98b71ad84f3024c7541412f02124a26d327","essentia_git_sha":"v2.1_beta1-228-g260734a","extractor":"music 1.0","gaia":"2.4-dev","gaia_git_sha":"857329b","models_essentia_git_sha":"v2.1_beta1"}},"ismir04_rhythm":{"all":{"ChaChaCha":0.0192334204912,"Jive":0.0024842931889,"Quickstep":0.00125424575526,"Rumba-American":0.00422172388062,"Rumba-International":0.00432139122859,"Rumba-Misc":0.0188917256892,"Samba":0.00263565615751,"Tango":0.483947992325,"VienneseWaltz":0.454196959734,"Waltz":0.00881258957088},"probability":0.483947992325,"value":"Tango","version":{"essentia":"2.1-beta1","essentia_build_sha":"8e24b98b71ad84f3024c7541412f02124a26d327","essentia_git_sha":"v2.1_beta1-228-g260734a","extractor":"music 1.0","gaia":"2.4-dev","gaia_git_sha":"857329b","models_essentia_git_sha":"v2.1_beta1"}},"mood_acoustic":{"all":{"acoustic":0.802794396877,"not_acoustic":0.197205603123},"probability":0.802794396877,"value":"acoustic","version":{"essentia":"2.1-beta1","essentia_build_sha":"8e24b98b71ad84f3024c7541412f02124a26d327","essentia_git_sha":"v2.1_beta1-228-g260734a","extractor":"music 1.0","gaia":"2.4-dev","gaia_git_sha":"857329b","models_essentia_git_sha":"v2.1_beta1"}},"mood_aggressive":{"all":{"aggressive":0.0447181239724,"not_aggressive":0.955281853676},"probability":0.955281853676,"value":"not_aggressive","version":{"essentia":"2.1-beta1","essentia_build_sha":"8e24b98b71ad84f3024c7541412f02124a26d327","essentia_git_sha":"v2.1_beta1-228-g260734a","extractor":"music 1.0","gaia":"2.4-dev","gaia_git_sha":"857329b","models_essentia_git_sha":"v2.1_beta1"}},"mood_electronic":{"all":{"electronic":0.0618874505162,"not_electronic":0.938112556934},"probability":0.938112556934,"value":"not_electronic","version":{"essentia":"2.1-beta1","essentia_build_sha":"8e24b98b71ad84f3024c7541412f02124a26d327","essentia_git_sha":"v2.1_beta1-228-g260734a","extractor":"music 1.0","gaia":"2.4-dev","gaia_git_sha":"857329b","models_essentia_git_sha":"v2.1_beta1"}},"mood_happy":{"all":{"happy":0.602624535561,"not_happy":0.397375464439},"probability":0.602624535561,"value":"happy","version":{"essentia":"2.1-beta1","essentia_build_sha":"8e24b98b71ad84f3024c7541412f02124a26d327","essentia_git_sha":"v2.1_beta1-228-g260734a","extractor":"music 1.0","gaia":"2.4-dev","gaia_git_sha":"857329b","models_essentia_git_sha":"v2.1_beta1"}},"mood_party":{"all":{"not_party":0.936334311962,"party":0.0636656805873},"probability":0.936334311962,"value":"not_party","version":{"essentia":"2.1-beta1","essentia_build_sha":"8e24b98b71ad84f3024c7541412f02124a26d327","essentia_git_sha":"v2.1_beta1-228-g260734a","extractor":"music 1.0","gaia":"2.4-dev","gaia_git_sha":"857329b","models_essentia_git_sha":"v2.1_beta1"}},"mood_relaxed":{"all":{"not_relaxed":0.215604871511,"relaxed":0.784395098686},"probability":0.784395098686,"value":"relaxed","version":{"essentia":"2.1-beta1","essentia_build_sha":"8e24b98b71ad84f3024c7541412f02124a26d327","essentia_git_sha":"v2.1_beta1-228-g260734a","extractor":"music 1.0","gaia":"2.4-dev","gaia_git_sha":"857329b","models_essentia_git_sha":"v2.1_beta1"}},"mood_sad":{"all":{"not_sad":0.1907466501,"sad":0.809253334999},"probability":0.809253334999,"value":"sad","version":{"essentia":"2.1-beta1","essentia_build_sha":"8e24b98b71ad84f3024c7541412f02124a26d327","essentia_git_sha":"v2.1_beta1-228-g260734a","extractor":"music 1.0","gaia":"2.4-dev","gaia_git_sha":"857329b","models_essentia_git_sha":"v2.1_beta1"}},"moods_mirex":{"all":{"Cluster1":0.114376589656,"Cluster2":0.477725744247,"Cluster3":0.104196615517,"Cluster4":0.152647465467,"Cluster5":0.151053577662},"probability":0.477725744247,"value":"Cluster2","version":{"essentia":"2.1-beta1","essentia_build_sha":"8e24b98b71ad84f3024c7541412f02124a26d327","essentia_git_sha":"v2.1_beta1-228-g260734a","extractor":"music 1.0","gaia":"2.4-dev","gaia_git_sha":"857329b","models_essentia_git_sha":"v2.1_beta1"}},"timbre":{"all":{"bright":0.975071132183,"dark":0.0249288864434},"probability":0.975071132183,"value":"bright","version":{"essentia":"2.1-beta1","essentia_build_sha":"8e24b98b71ad84f3024c7541412f02124a26d327","essentia_git_sha":"v2.1_beta1-228-g260734a","extractor":"music 1.0","gaia":"2.4-dev","gaia_git_sha":"857329b","models_essentia_git_sha":"v2.1_beta1"}},"tonal_atonal":{"all":{"atonal":0.250293195248,"tonal":0.749706804752},"probability":0.749706804752,"value":"tonal","version":{"essentia":"2.1-beta1","essentia_build_sha":"8e24b98b71ad84f3024c7541412f02124a26d327","essentia_git_sha":"v2.1_beta1-228-g260734a","extractor":"music 1.0","gaia":"2.4-dev","gaia_git_sha":"857329b","models_essentia_git_sha":"v2.1_beta1"}},"voice_instrumental":{"all":{"instrumental":0.212889805436,"voice":0.787110209465},"probability":0.787110209465,"value":"voice","version":{"essentia":"2.1-beta1","essentia_build_sha":"8e24b98b71ad84f3024c7541412f02124a26d327","essentia_git_sha":"v2.1_beta1-228-g260734a","extractor":"music 1.0","gaia":"2.4-dev","gaia_git_sha":"857329b","models_essentia_git_sha":"v2.1_beta1"}}},"metadata":{"audio_properties":{"analysis_sample_rate":44100,"bit_rate":0,"codec":"flac","downmix":"mix","equal_loudness":0,"length":225.333328247,"lossless":1,"md5_encoded":"8e1f6e034d33a290ad325c459405076b","replay_gain":-14.8634414673},"tags":{"album":["Tears...for truth \uff5etrue tears\u30a4\u30e1\u30fc\u30b8\u30bd\u30f3\u30b0\u96c6\uff5e"],"albumartist":["Various Artists"],"albumartistsort":["Various Artists"],"albumsort":["Tears...for truth \uff5etrue tears\u30a4\u30e1\u30fc\u30b8\u30bd\u30f3\u30b0\u96c6\uff5e (2008-04-16, Various Artists, 06dd5bb3-4fa2-49dc-90e6-349913d5cb44)"],"artist":["\u7d50\u57ce\u30a2\u30a4\u30e9"],"artists":["\u7d50\u57ce\u30a2\u30a4\u30e9"],"artistsort":["Yuuki, Aira"],"asin":["B001340ZVG"],"barcode":["4540774507634"],"catalognumber":["LACA-5763"],"compilation":["1"],"date":["2008-04-16"],"discnumber":["1"],"disctotal":["1"],"file_name":"02 - \u7d50\u57ce\u30a2\u30a4\u30e9 - No reason_.flac","genre":["True Tears"],"isrc":["JPI100800697"],"label":["Lantis"],"lyricist":["\u7551\u4e9c\u8cb4"],"media":["CD"],"musicbrainz_albumartistid":["89ad4ac3-39f7-470e-963a-56509c546377"],"musicbrainz_albumid":["06dd5bb3-4fa2-49dc-90e6-349913d5cb44"],"musicbrainz_artistid":["5a308af7-09a9-4823-91db-8fee35cfb470"],"musicbrainz_recordingid":["15ca5a84-6a80-4c76-9e2f-9650e5c4c7a5"],"musicbrainz_releasegroupid":["d14418f8-1239-4be8-904f-0cd658ea4816"],"musicbrainz_releasetrackid":["0a41e033-ce0f-3b9b-b3e9-ba972bc4cf0f"],"musicbrainz_workid":["dc8fcb36-fddf-3bfe-a1ec-55f22b88992f"],"musicip_puid":["c1bc6419-9773-ed52-ce15-20d6f3b6140b"],"originaldate":["2008-04-16"],"releasecountry":["JP"],"releasestatus":["official"],"releasetype":["album"],"replaygain_album_gain":["-10.650000"],"replaygain_album_peak":["1.000000"],"replaygain_track_gain":["-9.540000"],"replaygain_track_peak":["0.997833"],"script":["Jpan"],"title":["No reason?"],"totaldiscs":["1"],"totaltracks":["10"],"tracknumber":["2"],"tracktotal":["10"],"work":["No reason?"]},"version":{"highlevel":{"essentia":"2.1-beta1","essentia_build_sha":"8e24b98b71ad84f3024c7541412f02124a26d327","essentia_git_sha":"v2.1_beta1-228-g260734a","extractor":"music 1.0","gaia":"2.4-dev","gaia_git_sha":"857329b","models_essentia_git_sha":"v2.1_beta1"},"lowlevel":{"essentia":"2.1-beta1","essentia_build_sha":"5a55991247aa8bc5301991e5ebe36927b56abb96","essentia_git_sha":"v2.1_beta1-6-g5578087","extractor":"music 1.0"}}}}