{"highlevel":{"danceability":{"all":{"danceable":0.999999880791,"not_danceable":1.00000008274e-7},"probability":0.999999880791,"value":"danceable","version":{"essentia":"2.1-beta1","essentia_build_sha":"8e24b98b71ad84f3024c7541412f02124a26d327","essentia_git_sha":"v2.1_beta1-228-g260734a","extractor":"music 1.0","gaia":"2.4-dev","gaia_git_sha":"857329b","models_essentia_git_sha":"v2.1_beta1"}},"gender":{"all":{"female":0.622126698494,"male":0.377873301506},"probability":0.622126698494,"value":"female","version":{"essentia":"2.1-beta1","essentia_build_sha":"8e24b98b71ad84f3024c7541412f02124a26d327","essentia_git_sha":"v2.1_beta1-228-g260734a","extractor":"music 1.0","gaia":"2.4-dev","gaia_git_sha":"857329b","models_essentia_git_sha":"v2.1_beta1"}},"genre_dortmund":{"all":{"alternative":0.0133197372779,"blues":0.00287847290747,"electronic":0.949267804623,"folkcountry":0.0171173065901,"funksoulrnb":0.000370207824744,"jazz":0.0121010020375,"pop":0.00143916218076,"raphiphop":0.000148521488882,"rock":0.00335778249428},"probability":0.949267804623,"value":"electronic","version":{"essentia":"2.1-beta1","essentia_build_sha":"8e24b98b71ad84f3024c7541412f02124a26d327","essentia_git_sha":"v2.1_beta1-228-g260734a","extractor":"music 1.0","gaia":"2.4-dev","gaia_git_sha":"857329b","models_essentia_git_sha":"v2.1_beta1"}},"genre_electronic":{"all":{"ambient":0.956511795521,"dnb":0.00112185569014,"house":0.0112580377609,"techno":0.00413361610845,"trance":0.0269746780396},"probability":0.956511795521,"value":"ambient","version":{"essentia":"2.1-beta1","essentia_build_sha":"8e24b98b71ad84f3024c7541412f02124a26d327","essentia_git_sha":"v2.1_beta1-228-g260734a","extractor":"music 1.0","gaia":"2.4-dev","gaia_git_sha":"857329b","models_essentia_git_sha":"v2.1_beta1"}},"genre_rosamerica":{"all":{"cla":0.0154699468985,"dan":0.0042541208677,"hip":0.00946521013975,"jaz":0.48084166646,"pop":0.325404495001,"rhy":0.152666538954,"roc":0.00254987040535,"spe":0.0093481503427},"probability":0.48084166646,"value":"jaz","version":{"essentia":"2.1-beta1","essentia_build_sha":"8e24b98b71ad84f3024c7541412f02124a26d327","essentia_git_sha":"v2.1_beta1-228-g260734a","extractor":"music 1.0","gaia":"2.4-dev","gaia_git_sha":"857329b","models_essentia_git_sha":"v2.1_beta1"}},"genre_tzanetakis":{"all":{"blu":1.13367287766e-14,"cla":3.04301668499e-14,"cou":1.17068559165e-14,"dis":4.21400551444e-14,"hip":2.93635795746e-14,"jaz":0.999999940395,"met":2.0000017642e-8,"pop":2.0000017642e-8,"reg":2.50000233848e-8,"roc":1.66666822565e-8},"probability":0.999999940395,"value":"jaz","version":{"essentia":"2.1-beta1","essentia_build_sha":"8e24b98b71ad84f3024c7541412f02124a26d327","essentia_git_sha":"v2.1_beta1-228-g260734a","extractor":"music 1.0","gaia":"2.4-dev","gaia_git_sha":"857329b","models_essentia_git_sha":"v2.1_beta1"}},"ismir04_rhythm":{"all":{"ChaChaCha":0.00861661415547,"Jive":0.000583430228289,"Quickstep":0.000706011138391,"Rumba-American":0.00307546765544,"Rumba-International":0.0102450670674,"Rumba-Misc":0.0420578345656,"Samba":0.00359560898505,"Tango":0.00889522768557,"VienneseWaltz":0.907093346119,"Waltz":0.0151313692331},"probability":0.907093346119,"value":"VienneseWaltz","version":{"essentia":"2.1-beta1","essentia_build_sha":"8e24b98b71ad84f3024c7541412f02124a26d327","essentia_git_sha":"v2.1_beta1-228-g260734a","extractor":"music 1.0","gaia":"2.4-dev","gaia_git_sha":"857329b","models_essentia_git_sha":"v2.1_beta1"}},"mood_acoustic":{"all":{"acoustic":0.0955903604627,"not_acoustic":0.904409646988},"probability":0.904409646988,"value":"not_acoustic","version":{"essentia":"2.1-beta1","essentia_build_sha":"8e24b98b71ad84f3024c7541412f02124a26d327","essentia_git_sha":"v2.1_beta1-228-g260734a","extractor":"music 1.0","gaia":"2.4-dev","gaia_git_sha":"857329b","models_essentia_git_sha":"v2.1_beta1"}},"mood_aggressive":{"all":{"aggressive":0.999999880791,"not_aggressive":1.00000008274e-7},"probability":0.999999880791,"value":"aggressive","version":{"essentia":"2.1-beta1","essentia_build_sha":"8e24b98b71ad84f3024c7541412f02124a26d327","essentia_git_sha":"v2.1_beta1-228-g260734a","extractor":"music 1.0","gaia":"2.4-dev","gaia_git_sha":"857329b","models_essentia_git_sha":"v2.1_beta1"}},"mood_electronic":{"all":{"electronic":0.979391694069,"not_electronic":0.0206082761288},"probability":0.979391694069,"value":"electronic","version":{"essentia":"2.1-beta1","essentia_build_sha":"8e24b98b71ad84f3024c7541412f02124a26d327","essentia_git_sha":"v2.1_beta1-228-g260734a","extractor":"music 1.0","gaia":"2.4-dev","gaia_git_sha":"857329b","models_essentia_git_sha":"v2.1_beta1"}},"mood_happy":{"all":{"happy":0.139750689268,"not_happy":0.860249340534},"probability":0.860249340534,"value":"not_happy","version":{"essentia":"2.1-beta1","essentia_build_sha":"8e24b98b71ad84f3024c7541412f02124a26d327","essentia_git_sha":"v2.1_beta1-228-g260734a","extractor":"music 1.0","gaia":"2.4-dev","gaia_git_sha":"857329b","models_essentia_git_sha":"v2.1_beta1"}},"mood_party":{"all":{"not_party":0.999984204769,"party":0.0000157784197654},"probability":0.999984204769,"value":"not_party","version":{"essentia":"2.1-beta1","essentia_build_sha":"8e24b98b71ad84f3024c7541412f02124a26d327","essentia_git_sha":"v2.1_beta1-228-g260734a","extractor":"music 1.0","gaia":"2.4-dev","gaia_git_sha":"857329b","models_essentia_git_sha":"v2.1_beta1"}},"mood_relaxed":{"all":{"not_relaxed":0.191182896495,"relaxed":0.808817088604},"probability":0.808817088604,"value":"relaxed","version":{"essentia":"2.1-beta1","essentia_build_sha":"8e24b98b71ad84f3024c7541412f02124a26d327","essentia_git_sha":"v2.1_beta1-228-g260734a","extractor":"music 1.0","gaia":"2.4-dev","gaia_git_sha":"857329b","models_essentia_git_sha":"v2.1_beta1"}},"mood_sad":{"all":{"not_sad":0.212611198425,"sad":0.787388801575},"probability":0.787388801575,"value":"sad","version":{"essentia":"2.1-beta1","essentia_build_sha":"8e24b98b71ad84f3024c7541412f02124a26d327","essentia_git_sha":"v2.1_beta1-228-g260734a","extractor":"music 1.0","gaia":"2.4-dev","gaia_git_sha":"857329b","models_essentia_git_sha":"v2.1_beta1"}},"moods_mirex":{"all":{"Cluster1":0.0772226452827,"Cluster2":0.0444035679102,"Cluster3":0.227747857571,"Cluster4":0.0306320842355,"Cluster5":0.61999386549},"probability":0.61999386549,"value":"Cluster5","version":{"essentia":"2.1-beta1","essentia_build_sha":"8e24b98b71ad84f3024c7541412f02124a26d327","essentia_git_sha":"v2.1_beta1-228-g260734a","extractor":"music 1.0","gaia":"2.4-dev","gaia_git_sha":"857329b","models_essentia_git_sha":"v2.1_beta1"}},"timbre":{"all":{"bright":0.180328503251,"dark":0.81967151165},"probability":0.81967151165,"value":"dark","version":{"essentia":"2.1-beta1","essentia_build_sha":"8e24b98b71ad84f3024c7541412f02124a26d327","essentia_git_sha":"v2.1_beta1-228-g260734a","extractor":"music 1.0","gaia":"2.4-dev","gaia_git_sha":"857329b","models_essentia_git_sha":"v2.1_beta1"}},"tonal_atonal":{"all":{"atonal":0.242228984833,"tonal":0.757771015167},"probability":0.757771015167,"value":"tonal","version":{"essentia":"2.1-beta1","essentia_build_sha":"8e24b98b71ad84f3024c7541412f02124a26d327","essentia_git_sha":"v2.1_beta1-228-g260734a","extractor":"music 1.0","gaia":"2.4-dev","gaia_git_sha":"857329b","models_essentia_git_sha":"v2.1_beta1"}},"voice_instrumental":{"all":{"instrumental":0.946192502975,"voice":0.0538074932992},"probability":0.946192502975,"value":"instrumental","version":{"essentia":"2.1-beta1","essentia_build_sha":"8e24b98b71ad84f3024c7541412f02124a26d327","essentia_git_sha":"v2.1_beta1-228-g260734a","extractor":"music 1.0","gaia":"2.4-dev","gaia_git_sha":"857329b","models_essentia_git_sha":"v2.1_beta1"}}},"metadata":{"audio_properties":{"analysis_sample_rate":44100,"bit_rate":0,"codec":"flac","downmix":"mix","equal_loudness":0,"length":260.026672363,"lossless":1,"md5_encoded":"1920e6f80cec75e478f0ed7e19619852","replay_gain":-12.2601680756},"tags":{"album":["\u305f\u3063\u305f1\u3064\u306e\u60f3\u3044"],"albumartist":["KOKIA"],"albumartistsort":["KOKIA"],"artist":["KOKIA"],"artistsort":["KOKIA"],"date":["2008-01-23"],"discnumber":["1"],"disctotal":["1"],"file_name":"2 - \u751f\u307e\u308c\u305f\u3066\u306e\u767d.flac","musicbrainz_albumartistid":["9e090eeb-8e2b-441c-b892-5dad97b67fee"],"musicbrainz_albumid":["95977ebc-d5e3-478c-a23d-e8a91f2499d6"],"musicbrainz_artistid":["9e090eeb-8e2b-441c-b892-5dad97b67fee"],"musicbrainz_recordingid":["0634a20f-842e-43e7-a78c-e97abfb9c1c5"],"musicbrainz_releasegroupid":["15fb121f-bd93-3e96-8c1c-d83c7ffea8b8"],"releasecountry":["JP"],"releasetype":["single"],"replaygain_album_gain":["-8.20 dB"],"replaygain_album_peak":["0.98870850"],"replaygain_reference_loudness":["89.0 dB"],"replaygain_track_gain":["-6.87 dB"],"replaygain_track_peak":["0.95501709"],"title":["\u751f\u307e\u308c\u305f\u3066\u306e\u767d"],"totaldiscs":["1"],"totaltracks":["4"],"tracknumber":["2"],"tracktotal":["4"]},"version":{"highlevel":{"essentia":"2.1-beta1","essentia_build_sha":"8e24b98b71ad84f3024c7541412f02124a26d327","essentia_git_sha":"v2.1_beta1-228-g260734a","extractor":"music 1.0","gaia":"2.4-dev","gaia_git_sha":"857329b","models_essentia_git_sha":"v2.1_beta1"},"lowlevel":{"essentia":"2.1-beta1","essentia_build_sha":"de1f7ffc9d3406fe9025cc52cfcd6ebfe2259f32","essentia_git_sha":"v2.1_beta1-5-gf9dded9","extractor":"music 1.0"}}}}